partitionpy/__init__.py
partitionpy/cga.py
partitionpy/ckk.py
partitionpy/complete_base.py
partitionpy/kckk.py
partitionpy/kk.py
partitionpy/naive_greedy.py
partitionpy/types.py
partitionpy-1.0.0.dist-info/METADATA
partitionpy-1.0.0.dist-info/WHEEL
partitionpy-1.0.0.dist-info/licenses/LICENSE
partitionpy-1.0.0.dist-info/RECORD
