Metadata-Version: 2.1
Name: partitionpy
Version: 1.0.0
Summary: A collection of PARTITION algorithms
Project-URL: Homepage, https://github.com/llueder/partitionpy
Project-URL: Bug Tracker, https://github.com/llueder/partitionpy/issues
Author-email: Lasse Lüder <lasse.lueder@tuhh.de>
License-File: LICENSE
Classifier: License :: OSI Approved :: GNU General Public License v3 (GPLv3)
Classifier: Operating System :: OS Independent
Classifier: Programming Language :: Python :: 3
Requires-Python: >=3.7
